.project
.pydevproject
AUTHORS
ChangeLog
LICENSE
README.exabgp
README.rst
install_bagpipe_bgp.sh
requirements.txt
setup.cfg
setup.py
bagpipe/__init__.py
bagpipe/bgp/__init__.py
bagpipe/bgp/bgp_daemon.py
bagpipe/bgp/fakerr.py
bagpipe/bgp/rest_api.py
bagpipe/bgp/cli/__init__.py
bagpipe/bgp/cli/looking_glass.py
bagpipe/bgp/cli/rest_attach.py
bagpipe/bgp/common/__init__.py
bagpipe/bgp/common/exceptions.py
bagpipe/bgp/common/logDecorator.py
bagpipe/bgp/common/looking_glass.py
bagpipe/bgp/common/net_utils.py
bagpipe/bgp/common/run_command.py
bagpipe/bgp/common/utils.py
bagpipe/bgp/engine/__init__.py
bagpipe/bgp/engine/bgp_manager.py
bagpipe/bgp/engine/bgp_peer_worker.py
bagpipe/bgp/engine/exabgp_peer_worker.py
bagpipe/bgp/engine/route_table_manager.py
bagpipe/bgp/engine/tracker_worker.py
bagpipe/bgp/engine/worker.py
bagpipe/bgp/tests/__init__.py
bagpipe/bgp/tests/test_route_table_manager.py
bagpipe/bgp/tests/test_tracker_worker.py
bagpipe/bgp/tests/test_vpn_instance.py
bagpipe/bgp/vpn/__init__.py
bagpipe/bgp/vpn/dataplane_drivers.py
bagpipe/bgp/vpn/label_allocator.py
bagpipe/bgp/vpn/vpn_instance.py
bagpipe/bgp/vpn/evpn/__init__.py
bagpipe/bgp/vpn/evpn/linux_vxlan.py
bagpipe/bgp/vpn/ipvpn/__init__.py
bagpipe/bgp/vpn/ipvpn/mpls_linux_dataplane.py
bagpipe/bgp/vpn/ipvpn/mpls_ovs_dataplane.py
bagpipe/exabgp/COPYRIGHT
bagpipe/exabgp/__init__.py
bagpipe/exabgp/application.py
bagpipe/exabgp/configuration.py
bagpipe/exabgp/daemon.py
bagpipe/exabgp/debug.py
bagpipe/exabgp/log.py
bagpipe/exabgp/processes.py
bagpipe/exabgp/utils.py
bagpipe/exabgp/version.py
bagpipe/exabgp/message/__init__.py
bagpipe/exabgp/message/keepalive.py
bagpipe/exabgp/message/nop.py
bagpipe/exabgp/message/notification.py
bagpipe/exabgp/message/open.py
bagpipe/exabgp/message/update/__init__.py
bagpipe/exabgp/message/update/attributes.py
bagpipe/exabgp/message/update/eor.py
bagpipe/exabgp/message/update/flow.py
bagpipe/exabgp/message/update/route.py
bagpipe/exabgp/message/update/attribute/__init__.py
bagpipe_bgp.egg-info/PKG-INFO
bagpipe_bgp.egg-info/SOURCES.txt
bagpipe_bgp.egg-info/dependency_links.txt
bagpipe_bgp.egg-info/entry_points.txt
bagpipe_bgp.egg-info/not-zip-safe
bagpipe_bgp.egg-info/pbr.json
bagpipe_bgp.egg-info/requires.txt
bagpipe_bgp.egg-info/top_level.txt
