Metadata-Version: 1.1
Name: bagpipe-bgp
Version: 1.80.0
Summary: Lightweight implementation of BGP IP VPN and E-VPN
Home-page: https://github.com/Orange-OpenSource/bagpipe-bgp
Author: Thomas MORIN
Author-email: thomas.morin@orange.com
License: Apache-2
Platform: UNKNOWN
Classifier: Environment :: No Input/Output (Daemon)
Classifier: Intended Audience :: Developers
Classifier: Intended Audience :: System Administrators
Classifier: Intended Audience :: Telecommunications Industry
Classifier: License :: OSI Approved :: Apache Software License
Classifier: Operating System :: POSIX :: Linux
Classifier: Programming Language :: Python
Classifier: Programming Language :: Python :: 2
Classifier: Programming Language :: Python :: 2.7
